storytelling_mcp/__init__.py
storytelling_mcp/server.py
storytelling_mcp/setup.py
storytelling_mcp-0.1.8.dist-info/METADATA
storytelling_mcp-0.1.8.dist-info/WHEEL
storytelling_mcp-0.1.8.dist-info/entry_points.txt
storytelling_mcp-0.1.8.dist-info/top_level.txt
storytelling_mcp-0.1.8.dist-info/RECORD
