Metadata-Version: 2.4
Name: storytelling-mcp
Version: 0.1.8
Summary: Model Context Protocol server for storytelling - AI-powered narrative generation
Author-email: JGWill <jgi@jgwill.com>
Maintainer: JGWill
License: MIT
Project-URL: Homepage, https://github.com/jgwill/storytelling
Project-URL: Repository, https://github.com/jgwill/storytelling
Project-URL: Documentation, https://github.com/jgwill/storytelling/blob/main/mcp/README.md
Project-URL: Issues, https://github.com/jgwill/storytelling/issues
Keywords: mcp,model-context-protocol,storytelling,narrative-generation,ai-writing,langchain,langgraph,llm
Classifier: Development Status :: 4 - Beta
Classifier: Intended Audience :: Developers
Classifier: Intended Audience :: End Users/Desktop
Classifier: Programming Language :: Python :: 3
Classifier: Programming Language :: Python :: 3.9
Classifier: Programming Language :: Python :: 3.10
Classifier: Programming Language :: Python :: 3.11
Classifier: Programming Language :: Python :: 3.12
Classifier: Topic :: Text Processing
Classifier: Topic :: Scientific/Engineering :: Artificial Intelligence
Classifier: Topic :: Software Development :: Libraries :: Python Modules
Classifier: License :: OSI Approved :: MIT License
Requires-Python: >=3.9
Requires-Dist: mcp>=0.1.0
Provides-Extra: dev
Requires-Dist: pytest>=7.0.0; extra == "dev"
Requires-Dist: pytest-cov>=4.0.0; extra == "dev"
Requires-Dist: black>=23.0.0; extra == "dev"
Requires-Dist: isort>=5.12.0; extra == "dev"
Requires-Dist: flake8>=6.0.0; extra == "dev"
Requires-Dist: mypy>=1.0.0; extra == "dev"
Requires-Dist: pre-commit>=3.0.0; extra == "dev"
Requires-Dist: ruff>=0.1.0; extra == "dev"
Provides-Extra: test
Requires-Dist: pytest>=7.0; extra == "test"
Requires-Dist: pytest-cov>=4.0; extra == "test"
Requires-Dist: pytest-mock>=3.0; extra == "test"
